LICENSE
README.rst
setup.py
VAE/data.py
VAE/model.py
VAE/train.py
VAE/train_utils.py
VAE/utils.py
VAELLEMUR.egg-info/PKG-INFO
VAELLEMUR.egg-info/SOURCES.txt
VAELLEMUR.egg-info/dependency_links.txt
VAELLEMUR.egg-info/requires.txt
VAELLEMUR.egg-info/top_level.txt